circuitpython_miniethers/__init__.py
circuitpython_miniethers/keccak.py
circuitpython_miniethers/miniethers.py
circuitpython_miniethers-1.0.0.dist-info/licenses/LICENSE
circuitpython_miniethers-1.0.0.dist-info/METADATA
circuitpython_miniethers-1.0.0.dist-info/WHEEL
circuitpython_miniethers-1.0.0.dist-info/top_level.txt
circuitpython_miniethers-1.0.0.dist-info/RECORD
