Metadata-Version: 2.4
Name: circuitpython-miniethers
Version: 1.0.0
Summary: Circuitpython module for ethereum wallet creation and signing
Author-email: Shamba Chowdhury <shambachowdhury2@gmail.com>
License: MIT
Project-URL: Homepage, https://github.com/ShambaC/CircuitPython_MiniEthers
Keywords: adafruit,blinka,circuitpython,micropython,miniethers,ethereum
Classifier: Intended Audience :: Developers
Classifier: Topic :: Software Development :: Libraries
Classifier: Topic :: Software Development :: Embedded Systems
Classifier: Topic :: System :: Hardware
Classifier: License :: OSI Approved :: MIT License
Classifier: Programming Language :: Python :: 3
License-File: LICENSE
Requires-Dist: Adafruit-Blinka
Requires-Dist: circuitpython_hmac
Provides-Extra: optional
Dynamic: license-file
